gevent_utils.py
setup.py
gevent_utils.egg-info/PKG-INFO
gevent_utils.egg-info/SOURCES.txt
gevent_utils.egg-info/dependency_links.txt
gevent_utils.egg-info/top_level.txt