Metadata-Version: 1.0
Name: gevent-utils
Version: 0.0.2
Summary: miscellaneous gevent utilities
Home-page: http://traviscline.github.com/gevent-utils
Author: Travis Cline
Author-email: travis.cline@gmail.com
License: UNKNOWN
Platform: UNKNOWN
